vit/__init__.py
vit/action_manager.py
vit/actions.py
vit/application.py
vit/autocomplete.py
vit/base_list_box.py
vit/color.py
vit/color_mappings.py
vit/command_bar.py
vit/command_line.py
vit/config_parser.py
vit/debug.py
vit/denotation.py
vit/env.py
vit/event.py
vit/exception.py
vit/formatter_base.py
vit/help.py
vit/key_cache.py
vit/keybinding_parser.py
vit/list_batcher.py
vit/loader.py
vit/markers.py
vit/multi_widget.py
vit/option_parser.py
vit/pid_manager.py
vit/process.py
vit/readline.py
vit/registry.py
vit/task.py
vit/task_list.py
vit/uda.py
vit/util.py
vit/version.py
vit/xdg.py
vit/config/config.sample.ini
vit/formatter/__init__.py
vit/formatter/depends.py
vit/formatter/depends_count.py
vit/formatter/depends_indicator.py
vit/formatter/depends_list.py
vit/formatter/description.py
vit/formatter/description_combined.py
vit/formatter/description_count.py
vit/formatter/description_desc.py
vit/formatter/description_oneline.py
vit/formatter/description_truncated.py
vit/formatter/description_truncated_count.py
vit/formatter/due.py
vit/formatter/due_age.py
vit/formatter/due_countdown.py
vit/formatter/due_epoch.py
vit/formatter/due_formatted.py
vit/formatter/due_iso.py
vit/formatter/due_julian.py
vit/formatter/due_relative.py
vit/formatter/due_remaining.py
vit/formatter/end.py
vit/formatter/end_age.py
vit/formatter/end_countdown.py
vit/formatter/end_epoch.py
vit/formatter/end_iso.py
vit/formatter/end_julian.py
vit/formatter/end_relative.py
vit/formatter/end_remaining.py
vit/formatter/entry.py
vit/formatter/entry_age.py
vit/formatter/entry_countdown.py
vit/formatter/entry_epoch.py
vit/formatter/entry_formatted.py
vit/formatter/entry_iso.py
vit/formatter/entry_julian.py
vit/formatter/entry_relative.py
vit/formatter/entry_remaining.py
vit/formatter/id.py
vit/formatter/id_number.py
vit/formatter/markers.py
vit/formatter/modified.py
vit/formatter/modified_age.py
vit/formatter/modified_countdown.py
vit/formatter/modified_epoch.py
vit/formatter/modified_iso.py
vit-2.3.3.dist-info/AUTHORS.md
vit-2.3.3.dist-info/LICENSE
vit-2.3.3.dist-info/METADATA
vit-2.3.3.dist-info/WHEEL
vit-2.3.3.dist-info/entry_points.txt
vit-2.3.3.dist-info/top_level.txt
vit-2.3.3.dist-info/RECORD
