Metadata-Version: 2.2
Name: vit
Version: 2.3.3
Summary: Visual Interactive Taskwarrior full-screen terminal interface
Home-page: https://github.com/vit-project/vit
Author: Chad Phillips
Author-email: chad@apartmentlines.com
Keywords: taskwarrior,console,tui,text-user-interface
Classifier: Development Status :: 5 - Production/Stable
Classifier: License :: OSI Approved :: MIT License
Classifier: Environment :: Console
Classifier: Programming Language :: Python
Classifier: Natural Language :: English
Classifier: Topic :: Text Processing :: General
Requires-Python: >=3.7
License-File: LICENSE
License-File: AUTHORS.md
Requires-Dist: tasklib>=2.4.3
Requires-Dist: urwid>=2.1.2
Requires-Dist: backports.zoneinfo; python_version < "3.9"
Dynamic: author
Dynamic: author-email
Dynamic: classifier
Dynamic: description
Dynamic: description-content-type
Dynamic: home-page
Dynamic: keywords
Dynamic: requires-dist
Dynamic: requires-python
Dynamic: summary
